{
  "archetype": "OIL_GAS",
  "subStyleId": "OG_OFFSHORE",
  "subStyleName": "Offshore",
  "visualMetaphor": "The rig at dawn — ocean depth, amber horizon, subsurface power",
  "primaryColor": "#0a1a26",
  "accentColor": "#c19611",
  "bgColor": "#F2EEE8",
  "textColor": "#060F1A",
  "surfaceColor": "#081721",
  "secondaryAccent": "#476c7d",
  "fontDisplay": "Spectral",
  "fontBody": "Lato",
  "googleFonts": "https://fonts.googleapis.com/css2?family=Spectral:ital,wght@0,400;0,600;0,700;1,400&family=Lato:wght@300;400;700&display=swap",
  "borderRadius": "2px",
  "layoutStyle": "editorial-authority",
  "heroType": "asymmetric-left",
  "density": "balanced",
  "motionStyle": "reveal-on-scroll",
  "shadowStyle": "layered-elevation",
  "textureHint": "seismic data wave line at 4%",
  "uniqueElement": "Full-bleed offshore photography with dramatic text overlay at bottom",
  "uxPrinciple": "Powering Africa's energy future with reliable, sustainable oil and gas solutions.",
  "cssVariables": "--color-primary:#0a1a26; --color-accent:#c19611; --color-bg:#F2EEE8; --color-text:#060F1A; --color-surface:#081721; --color-secondary-accent:#476c7d; --font-display:Spectral; --font-body:Lato; --border-radius:2px; --motion-style:reveal-on-scroll; --shadow-style:layered-elevation"
}